milesianpy/__init__.py
milesianpy/common_operators.py
milesianpy/calculations/__init__.py
milesianpy/calculations/no_variable_calculation.py
milesianpy/parsers/__init__.py
milesianpy/parsers/basic_parser.py
milesianpy/parsers/number_parser.py
milesianpy/parsers/operator_parser.py
milesian-0.0.1.dist-info/METADATA
milesian-0.0.1.dist-info/WHEEL
milesian-0.0.1.dist-info/top_level.txt
milesian-0.0.1.dist-info/RECORD
