Metadata-Version: 2.1
Name: milesian
Version: 0.0.1
Summary: A math calculation package.
Author-email: "Anna St. Germain" <anna.stgermain885@gmail.com>
Requires-Python: >=3.8
